CHANGELOG.md
README.md
tuftelike/__init__.py
matplotlib_tufte-1.1.1.dist-info/LICENSE
matplotlib_tufte-1.1.1.dist-info/LICENSES/Apache-2.0.txt
matplotlib_tufte-1.1.1.dist-info/LICENSES/CC0-1.0.txt
matplotlib_tufte-1.1.1.dist-info/METADATA
matplotlib_tufte-1.1.1.dist-info/WHEEL
matplotlib_tufte-1.1.1.dist-info/RECORD
