Metadata-Version: 2.1
Name: matplotlib-tufte
Version: 1.1.1
Summary: Tufte-style plots for matplotlib
Home-page: https://gitlab.com/lemberger/matplotlib-tufte
License: Apache-2.0
Keywords: plotting,matplotlib
Author: Thomas Lemberger
Author-email: lembergerth@gmail.com
Requires-Python: >=3.7,<4.0
Classifier: Framework :: Matplotlib
Classifier: Intended Audience :: Education
Classifier: Intended Audience :: Science/Research
Classifier: License :: OSI Approved :: Apache Software License
Classifier: Programming Language :: Python :: 3
Classifier: Programming Language :: Python :: 3.7
Classifier: Programming Language :: Python :: 3.8
Classifier: Programming Language :: Python :: 3.9
Classifier: Programming Language :: Python :: 3.10
Classifier: Programming Language :: Python :: 3.11
Requires-Dist: matplotlib (>=3,<4)
Project-URL: Repository, https://gitlab.com/lemberger/matplotlib-tufte
